setup.py
weebly/__init__.py
weebly/tests.py
weebly/utils.py
weebly.egg-info/PKG-INFO
weebly.egg-info/SOURCES.txt
weebly.egg-info/dependency_links.txt
weebly.egg-info/not-zip-safe
weebly.egg-info/requires.txt
weebly.egg-info/top_level.txt