Metadata-Version: 1.0
Name: weebly
Version: 0.2
Summary: Python functions to interface with Weebly Cloud Api
Home-page: http://github.com/tkwon/weebly
Author: T Kwon
Author-email: tdkwon@gmail.com
License: MIT
Platform: UNKNOWN
